enigma_gubs_ian/__init__.py
enigma_gubs_ian/myfunctions.py
enigma_gubs_ian-0.1.0.dist-info/METADATA
enigma_gubs_ian-0.1.0.dist-info/WHEEL
enigma_gubs_ian-0.1.0.dist-info/top_level.txt
enigma_gubs_ian-0.1.0.dist-info/RECORD
