Metadata-Version: 2.1
Name: enigma-gubs-ian
Version: 0.1.0
Summary: Enigma machine linear algebra implementation
Home-page: UNKNOWN
Author: Gubs and Ian
License: UNKNOWN
Platform: UNKNOWN
Requires-Dist: numpy
Requires-Dist: flask
